[
  {
    "title": "Zorro",
    "url": "https://randomfox.ca/images/89.jpg",
    "date": "2025-07-07",
    "colors": [
      "#655028",
      "#d2ae7b",
      "#161509"
    ],
    "description": "Carnívoro, astuto, mamífero, canino, salvaje."
  },
  {
    "title": "Oso Panda",
    "url": "https://upload.wikimedia.org/wikipedia/commons/thumb/0/0f/Grosser_Panda.JPG/960px-Grosser_Panda.JPG",
    "date": "2025-07-07",
    "colors": [
      "#3f473a",
      "#dadccc",
      "#9ab59e"
    ],
    "description": "Mamífero, plantígrado, asiático, blanco, negro."
  },
  {
    "title": "Elefantes",
    "url": "https://files.worldwildlife.org/wwfcmsprod/images/elephants_at_water_hole_WW2122503_Anup_Shah/story_full_width/7ozyekgso2_Medium_WW2122503.jpg",
    "date": "2025-07-07",
    "colors": [
      "#4d443e",
      "#d4dbed",
      "#809fe3"
    ],
    "description": "Mamíferos grandes herbívoros inteligentes."
  },
  {
    "title": "Ardillas",
    "url": "https://i.pinimg.com/736x/bc/e9/94/bce9943e98e2fafba3a5cc88058e5231.jpg",
    "date": "2025-07-07",
    "colors": [
      "#63502f",
      "#c69c75",
      "#1c180b"
    ],
    "description": "Roedores pequeños arborícolas."
  },
  {
    "title": "Koalas",
    "url": "https://naukas.com/fx/uploads/2018/12/koalas-640x400.jpg",
    "date": "2025-07-07",
    "colors": [
      "#31382c",
      "#b7c0a6",
      "#718d50"
    ],
    "description": "Marsupiales arborícolas herbívoros australianos."
  },
  {
    "title": "Leopardo",
    "url": "https://animals.sandiegozoo.org/sites/default/files/2016-09/animals_hero_leopard_0.jpg",
    "date": "2025-07-07",
    "colors": [
      "#675540",
      "#c89a65",
      "#181d16"
    ],
    "description": "Felino grande, moteado."
  },
  {
    "title": "Leon",
    "url": "https://s1.significados.com/foto/leon-animal-salvaje-ok.jpg",
    "date": "2025-07-07",
    "colors": [
      "#444a13",
      "#d2a764",
      "#958433"
    ],
    "description": "Felino, grande, salvaje, africano, mamífero."
  },
  {
    "title": "Osos Polares",
    "url": "https://efeverde.com/wp-content/uploads/2022/01/osos-polar-pareja-cachorros.jpg",
    "date": "2025-07-07",
    "colors": [
      "#625f41",
      "#cecac3",
      "#171b0a"
    ],
    "description": "Mamíferos marinos depredadores árticos."
  },
  {
    "title": "Mapache",
    "url": "https://www.fundacionaquae.org/wp-content/uploads/2018/10/proteger-a-los-animales.jpg",
    "date": "2025-07-07",
    "colors": [
      "#6e613f",
      "#cdb8a5",
      "#1b1609"
    ],
    "description": "Mamífero omnívoro arborícola nocturno."
  },
  {
    "title": "Aguila",
    "url": "https://img.pikbest.com/ai/illus_our/20230422/1b08c2bf12d92dbd547c53aa0f6a9f07.jpg",
    "date": "2025-07-07",
    "colors": [
      "#29251a",
      "#bfb8ae",
      "#8f98a0"
    ],
    "description": "Ave rapaz, majestuosa y poderosa."
  },
  {
    "title": "Hipopotamos",
    "url": "https://img.freepik.com/foto-gratis/familia-hipopotamos-parque-nacional-kenia-africa_167946-43.jpg",
    "date": "2025-07-07",
    "colors": [
      "#a19887",
      "#33302f",
      "#533b37"
    ],
    "description": "Gigantes acuáticos herbívoros africanos."
  },
  {
    "title": "Perro",
    "url": "https://random.dog/32467-30239-4163.jpg",
    "date": "2025-07-17",
    "colors": [
      "#736c11",
      "#ded5c5",
      "#272204"
    ],
    "description": "Amigable, leal, compañero canino."
  }
]
